{
  "version": "6",
  "dialect": "sqlite",
  "id": "0e0ed89c-cf57-42d7-ba2f-3ba8becb4fac",
  "prevId": "00000000-0000-0000-0000-000000000000",
  "tables": {
    "analytics": {
      "name": "analytics",
      "columns": {
        "id": {
          "name": "id",
          "type": "text",
          "primaryKey": true,
          "notNull": true,
          "autoincrement": false
        },
        "project_id": {
          "name": "project_id",
          "type": "text",
          "primaryKey": false,
          "notNull": true,
          "autoincrement": false
        },
        "tour_id": {
          "name": "tour_id",
          "type": "text",
          "primaryKey": false,
          "notNull": false,
          "autoincrement": false
        },
        "user_id": {
          "name": "user_id",
          "type": "text",
          "primaryKey": false,
          "notNull": false,
          "autoincrement": false
        },
        "step_index": {
          "name": "step_index",
          "type": "integer",
          "primaryKey": false,
          "notNull": true,
          "autoincrement": false
        },
        "event_type": {
          "name": "event_type",
          "type": "text",
          "primaryKey": false,
          "notNull": true,
          "autoincrement": false
        },
        "timestamp": {
          "name": "timestamp",
          "type": "integer",
          "primaryKey": false,
          "notNull": true,
          "autoincrement": false
        }
      },
      "indexes": {
        "project_time_idx": {
          "name": "project_time_idx",
          "columns": [
            "project_id",
            "timestamp"
          ],
          "isUnique": false
        }
      },
      "foreignKeys": {
        "analytics_project_id_projects_id_fk": {
          "name": "analytics_project_id_projects_id_fk",
          "tableFrom": "analytics",
          "tableTo": "projects",
          "columnsFrom": [
            "project_id"
          ],
          "columnsTo": [
            "id"
          ],
          "onDelete": "cascade",
          "onUpdate": "no action"
        },
        "analytics_tour_id_tours_id_fk": {
          "name": "analytics_tour_id_tours_id_fk",
          "tableFrom": "analytics",
          "tableTo": "tours",
          "columnsFrom": [
            "tour_id"
          ],
          "columnsTo": [
            "id"
          ],
          "onDelete": "set null",
          "onUpdate": "no action"
        }
      },
      "compositePrimaryKeys": {},
      "uniqueConstraints": {}
    },
    "projects": {
      "name": "projects",
      "columns": {
        "id": {
          "name": "id",
          "type": "text",
          "primaryKey": true,
          "notNull": true,
          "autoincrement": false
        },
        "name": {
          "name": "name",
          "type": "text",
          "primaryKey": false,
          "notNull": true,
          "autoincrement": false
        },
        "api_key": {
          "name": "api_key",
          "type": "text",
          "primaryKey": false,
          "notNull": true,
          "autoincrement": false
        },
        "allowed_origins": {
          "name": "allowed_origins",
          "type": "text",
          "primaryKey": false,
          "notNull": true,
          "autoincrement": false
        },
        "created_at": {
          "name": "created_at",
          "type": "integer",
          "primaryKey": false,
          "notNull": true,
          "autoincrement": false
        }
      },
      "indexes": {
        "projects_api_key_unique": {
          "name": "projects_api_key_unique",
          "columns": [
            "api_key"
          ],
          "isUnique": true
        },
        "api_key_idx": {
          "name": "api_key_idx",
          "columns": [
            "api_key"
          ],
          "isUnique": false
        }
      },
      "foreignKeys": {},
      "compositePrimaryKeys": {},
      "uniqueConstraints": {}
    },
    "tours": {
      "name": "tours",
      "columns": {
        "id": {
          "name": "id",
          "type": "text",
          "primaryKey": true,
          "notNull": true,
          "autoincrement": false
        },
        "project_id": {
          "name": "project_id",
          "type": "text",
          "primaryKey": false,
          "notNull": true,
          "autoincrement": false
        },
        "context_key": {
          "name": "context_key",
          "type": "text",
          "primaryKey": false,
          "notNull": true,
          "autoincrement": false
        },
        "version_hash": {
          "name": "version_hash",
          "type": "text",
          "primaryKey": false,
          "notNull": true,
          "autoincrement": false
        },
        "steps_json": {
          "name": "steps_json",
          "type": "text",
          "primaryKey": false,
          "notNull": true,
          "autoincrement": false
        },
        "element_fingerprints": {
          "name": "element_fingerprints",
          "type": "text",
          "primaryKey": false,
          "notNull": false,
          "autoincrement": false
        },
        "is_active": {
          "name": "is_active",
          "type": "integer",
          "primaryKey": false,
          "notNull": true,
          "autoincrement": false,
          "default": true
        },
        "created_at": {
          "name": "created_at",
          "type": "integer",
          "primaryKey": false,
          "notNull": true,
          "autoincrement": false
        },
        "updated_at": {
          "name": "updated_at",
          "type": "integer",
          "primaryKey": false,
          "notNull": true,
          "autoincrement": false
        }
      },
      "indexes": {
        "context_hash_idx": {
          "name": "context_hash_idx",
          "columns": [
            "context_key",
            "version_hash"
          ],
          "isUnique": false
        }
      },
      "foreignKeys": {
        "tours_project_id_projects_id_fk": {
          "name": "tours_project_id_projects_id_fk",
          "tableFrom": "tours",
          "tableTo": "projects",
          "columnsFrom": [
            "project_id"
          ],
          "columnsTo": [
            "id"
          ],
          "onDelete": "cascade",
          "onUpdate": "no action"
        }
      },
      "compositePrimaryKeys": {},
      "uniqueConstraints": {}
    },
    "user_progress": {
      "name": "user_progress",
      "columns": {
        "id": {
          "name": "id",
          "type": "text",
          "primaryKey": true,
          "notNull": true,
          "autoincrement": false
        },
        "project_id": {
          "name": "project_id",
          "type": "text",
          "primaryKey": false,
          "notNull": true,
          "autoincrement": false
        },
        "user_id": {
          "name": "user_id",
          "type": "text",
          "primaryKey": false,
          "notNull": true,
          "autoincrement": false
        },
        "tour_id": {
          "name": "tour_id",
          "type": "text",
          "primaryKey": false,
          "notNull": true,
          "autoincrement": false
        },
        "status": {
          "name": "status",
          "type": "text",
          "primaryKey": false,
          "notNull": true,
          "autoincrement": false
        },
        "completed_at": {
          "name": "completed_at",
          "type": "integer",
          "primaryKey": false,
          "notNull": false,
          "autoincrement": false
        },
        "created_at": {
          "name": "created_at",
          "type": "integer",
          "primaryKey": false,
          "notNull": true,
          "autoincrement": false
        }
      },
      "indexes": {
        "user_tour_idx": {
          "name": "user_tour_idx",
          "columns": [
            "user_id",
            "tour_id"
          ],
          "isUnique": false
        },
        "project_user_idx": {
          "name": "project_user_idx",
          "columns": [
            "project_id",
            "user_id"
          ],
          "isUnique": false
        }
      },
      "foreignKeys": {
        "user_progress_project_id_projects_id_fk": {
          "name": "user_progress_project_id_projects_id_fk",
          "tableFrom": "user_progress",
          "tableTo": "projects",
          "columnsFrom": [
            "project_id"
          ],
          "columnsTo": [
            "id"
          ],
          "onDelete": "cascade",
          "onUpdate": "no action"
        },
        "user_progress_tour_id_tours_id_fk": {
          "name": "user_progress_tour_id_tours_id_fk",
          "tableFrom": "user_progress",
          "tableTo": "tours",
          "columnsFrom": [
            "tour_id"
          ],
          "columnsTo": [
            "id"
          ],
          "onDelete": "cascade",
          "onUpdate": "no action"
        }
      },
      "compositePrimaryKeys": {},
      "uniqueConstraints": {}
    }
  },
  "enums": {},
  "_meta": {
    "schemas": {},
    "tables": {},
    "columns": {}
  }
}